setup.py
howto/__init__.py
howto/howto.py
howto.egg-info/PKG-INFO
howto.egg-info/SOURCES.txt
howto.egg-info/dependency_links.txt
howto.egg-info/entry_points.txt
howto.egg-info/requires.txt
howto.egg-info/top_level.txt