Metadata-Version: 1.1
Name: howto
Version: 0.1
Summary: stackoverflow code search tool
Home-page: https://github.com/sp4ke/howto
Author: Chakib Benziane
Author-email: chakib.benz@gmail.com
License: MIT
Keywords: howto help console code stackoverflow
Platform: UNKNOWN
Classifier: Development Status :: 3 - Alpha
Classifier: Environment :: Console
Classifier: Intended Audience :: Developers
Classifier: Programming Language :: Python :: 2
Classifier: Programming Language :: Python :: 2.7
Classifier: Topic :: Documentation
